prompt_manager/__init__.py
prompt_manager/cli.py
prompt_manager/llm_enhancement.py
prompt_manager/cli/__init__.py
prompt_manager/cli/llm_commands.py
tosins_prompt_manager-0.3.16.dist-info/METADATA
tosins_prompt_manager-0.3.16.dist-info/WHEEL
tosins_prompt_manager-0.3.16.dist-info/entry_points.txt
tosins_prompt_manager-0.3.16.dist-info/licenses/LICENSE
tosins_prompt_manager-0.3.16.dist-info/RECORD
