Metadata-Version: 2.4
Name: tosins-prompt-manager
Version: 0.3.16
Summary: Development workflow management system with memory tracking
License-Expression: MIT
License-File: LICENSE
Requires-Python: <3.14,>=3.9
Requires-Dist: click>=8.0.0
Requires-Dist: pyyaml>=6.0.1
Requires-Dist: typing-extensions>=4.7.1
Provides-Extra: dev
Requires-Dist: black; extra == 'dev'
Requires-Dist: flake8; extra == 'dev'
Requires-Dist: mypy; extra == 'dev'
Requires-Dist: pytest-cov>=4.0.0; extra == 'dev'
Requires-Dist: pytest-watch; extra == 'dev'
Requires-Dist: pytest>=7.0.0; extra == 'dev'
